mastermind/__init__.py
mastermind/__main__.py
mastermind/game/__init__.py
mastermind/game/board.py
mastermind/game/console.py
mastermind/game/director.py
mastermind/game/paint.py
mastermind/game/player.py
mastermind/game/roster.py
mastermind/game/score.py
hackermind-1.0.4.dist-info/LICENSE
hackermind-1.0.4.dist-info/METADATA
hackermind-1.0.4.dist-info/WHEEL
hackermind-1.0.4.dist-info/top_level.txt
hackermind-1.0.4.dist-info/RECORD
