Metadata-Version: 2.1
Name: hackermind
Version: 1.0.4
Summary: Crack the code in single- or multiplayer in this Mastermind masterpiece.
Home-page: https://github.com/cse210-spring21-team4/cse210-tc06
Author: Dalton W, Agnes H, Kelton G, Mireya V, Sarah A
Author-email: contact@daltonwillard.com
License: UNKNOWN
Project-URL: Bug Tracker, https://github.com/pypa/sampleproject/issues
Platform: UNKNOWN
Classifier: Programming Language :: Python :: 3
Classifier: License :: OSI Approved :: MIT License
Classifier: Operating System :: OS Independent
Requires-Python: >=3.6
License-File: LICENSE
